hdmems_plotlib/__init__.py
hdmems_plotlib/importers.py
hdmems_plotlib/query.py
hdmems_plotlib-1.0.2.dist-info/licenses/LICENSE
hdmems_plotlib-1.0.2.dist-info/METADATA
hdmems_plotlib-1.0.2.dist-info/WHEEL
hdmems_plotlib-1.0.2.dist-info/top_level.txt
hdmems_plotlib-1.0.2.dist-info/RECORD
