Metadata-Version: 2.4
Name: hdmems_plotlib
Version: 1.0.2
Summary: hdmems_plotlib can visualize S/Y/Z data generated by hdfem (after sweeping) or Ngspice simulators.
Author-email: yjc <y3332664073@hotmail.com>
Project-URL: Homepage, https://gitlab.com/aizhiqian/hdmems_plotlib
Keywords: s-parameters, visualization, EM simulation, ngspice, hdfem
Requires-Python: >=3.8
License-File: LICENSE
Requires-Dist: numpy
Requires-Dist: matplotlib
Dynamic: license-file
